MANIFEST.in
NEWS.txt
README.rst
setup.py
jarvis/__init__.py
jarvis/client.py
jarvis/commands.py
jarvis/cursedisplay.py
jarvis/mainloop.py
jarvis/osgqt.py
jarvis/qt.py
jarvis/qtdisplay.py
jarvis/rollbackimporter.py
jarvis/tracer.py
jarvis/wavehelper.py
jarvis.egg-info/PKG-INFO
jarvis.egg-info/SOURCES.txt
jarvis.egg-info/dependency_links.txt
jarvis.egg-info/entry_points.txt
jarvis.egg-info/not-zip-safe
jarvis.egg-info/top_level.txt
jarvis/agents/base.py
jarvis/agents/launcher/__init__.py
jarvis/emacs/__init__.py
jarvis/emacs/pseudolisp.py
jarvis/emacs/utils.py
jarvis/redis/__init__.py
jarvis/redis/base.py
jarvis/redis/dict.py
jarvis/redis/pubsub.py
jarvis/server/__init__.py
jarvis/server/broker.py
jarvis/server/frontend.py
jarvis/server/redisconnect.py
jarvis/server/state.py
jarvis/server/state_observer.py
jarvis/server/utils.py
jarvis/server/views.py
jarvis/server/tests/__init__.py
jarvis/server/tests/broker/__init__.py
jarvis/server/tests/broker/test_broker.py
jarvis/server/tests/routes/__init__.py
jarvis/server/tests/routes/test_routes.py
jarvis/tests/__init__.py
jarvis/tests/conf/__init__.py
jarvis/tests/conf/test_conf.py
jarvis/utils/__init__.py
jarvis/utils/conf.py