Metadata-Version: 1.0
Name: jarvis
Version: 0.1.3
Summary: Developer companion
Home-page: UNKNOWN
Author: Francois Lagunas
Author-email: francois.lagunas@gmail.com
License: MIT
Keywords: debugging
Platform: UNKNOWN
